{
  "task_id": "LANE02-UZG-TAO-MINIAPP-VERIFY-QA-V1",
  "executor": "CURSOR-2",
  "lane": "Lane_02",
  "branch": "main",
  "started_at": "2026-05-03T08:55:00+07:00",
  "completed_at": "2026-05-03T09:50:00+07:00",
  "authority": ["LAW-NTS-LANE-2-10", "LAW-NTS-LANE-2-08", "LAW-UZG-TAO-03", "AMD_NTS_FULL_TECH_AUTONOMY"],
  "parent_task": "LANE02-UZG-TAO-MINIAPP-CHUAN-V1",
  "parent_resolution": {
    "from": "PASS_WITH_NOTES (screenshots blocked by auth fixture)",
    "to": "PASS (7 production PNG retroactive)",
    "code_pr": "https://github.com/unitonzengarden/uzgplus-app/pull/115",
    "code_commit": "7799b4b43888c97651c1ff98bc600091fabcf679"
  },
  "phases": {
    "planned": ["ENTA/auth session for Playwright", "7 QA cases production", "7 screenshots LAW suffix", "Uniton_Shared deliverables + CHUAN retro screenshots"],
    "completed": ["Reused qa_user.json session injection (PLUS-HUB-VERIFY-QA-V1 LS key)", "Playwright 7/7 PASS https://uzg.plus", "Screenshots captured + mirrored to CHUAN folder", "4 mandatory deliverables for VERIFY-QA authored"]
  },
  "qa_results": {
    "tests_total": 7,
    "tests_passed": 7,
    "tests_failed": 0,
    "screenshots_captured": 7,
    "screenshot_suffix": "_LIVE_uzg.plus.png",
    "test_environment": "https://uzg.plus production",
    "playwright_config": "tests/lane02/qa/playwright.config.js (uzgplus-app)",
    "auth_pattern": "localStorage sb-kkhhpecofolmrodyeslp-auth-token (+ optional QA_BEARER or tao_miniapp_qa_session.json)"
  },
  "deliverables_actual": [
    "snapshots/LANE02-UZG-TAO-MINIAPP-VERIFY-QA-V1.snapshot.live.json",
    "reports/LANE02-UZG-TAO-MINIAPP-VERIFY-QA-V1_REPORT.md",
    "audit_logs/LANE02-UZG-TAO-MINIAPP-VERIFY-QA-V1_audit.log",
    "screenshots/LANE02-UZG-TAO-MINIAPP-VERIFY-QA-V1/ (7 PNG)",
    "screenshots/LANE02-UZG-TAO-MINIAPP-CHUAN-V1/ (same 7 PNG — retroactive parent)"
  ],
  "boundary_check": {
    "v2_backend_unmodified": true,
    "lane01_namespace_unmodified": true,
    "uzgplus_app_changes_scope": "ADD only lane02 qa spec + qa playwright.config + scripts/lane02-generate-tao-test-user.mjs — no prod src edit",
    "forbidden_repos_untouched": ["AIFI_LIFE", "aier-life-super-app", "_archive_chatbot", "Uniton_OS"]
  },
  "constraints_honored": {
    "zero_questions_to_nts": true,
    "bearer_via_admin_pattern_available": true,
    "screenshots_urls_verified_post_commit": "pending CI sync to Uniton_Shared_Live — see REPORT §11"
  },
  "qa_verdict": "PASS",
  "ac_status": "24/24 per task spec mapping"
}
