{
  "task_id": "LANE01-INH-CODE-01-UDNA",
  "executor": "Cursor",
  "lane": "Lane_01",
  "started_at": "2026-04-28T(estimated)",
  "completed_at": "2026-04-28T(estimated)",
  "duration_hours": null,
  "first_pr": "https://github.com/unitonzengarden/Uniton_OS/pull/5",
  "final_sha": "dd8d0a6e3d72cd62277159d3359183078bb99f45",
  "ac_pass": "(Cursor handoff via MSG-CURSOR-INFRA-AUTOMATION-COMPLETE; full report in Uniton_OS repo)",
  "boundary_pass": "PASS (per Cursor handoff)",
  "deliverables_paths": [
    "(in Uniton_OS repo) supabase/migrations/0032_aier_code_udna.sql",
    "(in Uniton_OS repo) reports/LANE01-INH-CODE-01-UDNA-LEDGER_REPORT.md (per cross-reference)"
  ],
  "key_outcomes": [
    "AIER Code UDNA ledger genesis applied to Uniton_OS Supabase",
    "Genesis hash: aa8aea32179ff8fe9d77db93b697447b2f4ac9b26c3853dac2c4c981ca81dc94",
    "aier_code_udna + aier_code_lineage tables LIVE with append-only triggers + RLS + ACL hardening",
    "Established pattern Tasks 4 + 6 mirrored (aier_code_* namespace, append-only, RLS, ACL)"
  ],
  "nts_clicks": 0,
  "backfill_note": "Backfilled by LANE01-LIVE-LEDGER-FOUNDATION on 2026-04-29. Original task executed by Cursor in Uniton_OS repo; this Live Ledger entry captures ecosystem-level record. Full report + audit log live in Uniton_OS repo."
}
