{
  "project_slug": "aier-code",
  "github_repo": "unitonzengarden/Uniton_Shared",
  "last_polled_at": "2026-05-01T10:44:46.659Z",
  "poll_status": "OK",
  "poll_token_source": "env:GH_TOKEN",
  "default_branch": "main",
  "is_private": true,
  "stars_count": 0,
  "head_sha": "c55c6740d23ed49befafd9c3e4af351a388bf89b",
  "head_message": "Lane01 P4S1: TAO shell + Overview deliverables (post-hot-fix) — uzg.plus/v3/app/tao/* LIVE [solo CLAC1] (#66)",
  "head_author": "Uniton Zen",
  "head_committed_at": "2026-05-01T10:16:05Z",
  "open_prs_count": 0,
  "open_issues_count": 0,
  "recent_commits_count_24h": 63,
  "recent_workflow_runs_count_24h": 20,
  "last_workflow_run_status": "in_progress",
  "last_workflow_run_name": "Ecosystem State Poll",
  "last_workflow_run_at": "2026-05-01T10:44:39Z",
  "api_rate_limit_remaining": "4875"
}
