{
  "project_slug": "aier-code",
  "github_repo": "unitonzengarden/Uniton_Shared",
  "last_polled_at": "2026-05-01T14:37:09.538Z",
  "poll_status": "OK",
  "poll_token_source": "env:GH_TOKEN",
  "default_branch": "main",
  "is_private": true,
  "stars_count": 0,
  "head_sha": "82d56f169c0b055cb332434c5101b8e46cf2c677",
  "head_message": "docs(p4s6): UZG+ Sprint 4.6 FINAL + PHASE 4 CLOSURE cross-publish (#72)",
  "head_author": "Uniton Zen",
  "head_committed_at": "2026-05-01T14:27:12Z",
  "open_prs_count": 0,
  "open_issues_count": 0,
  "recent_commits_count_24h": 66,
  "recent_workflow_runs_count_24h": 20,
  "last_workflow_run_status": "in_progress",
  "last_workflow_run_name": "Ecosystem State Poll",
  "last_workflow_run_at": "2026-05-01T14:36:53Z",
  "api_rate_limit_remaining": "4956"
}
